pretix_secuconnect/__init__.py
pretix_secuconnect/api_client.py
pretix_secuconnect/apps.py
pretix_secuconnect/payment.py
pretix_secuconnect/signals.py
pretix_secuconnect/urls.py
pretix_secuconnect/views.py
pretix_secuconnect/locale/django.pot
pretix_secuconnect/locale/de/LC_MESSAGES/django.mo
pretix_secuconnect/locale/de/LC_MESSAGES/django.po
pretix_secuconnect/locale/de_Informal/.gitkeep
pretix_secuconnect/locale/de_Informal/LC_MESSAGES/django.mo
pretix_secuconnect/locale/de_Informal/LC_MESSAGES/django.po
pretix_secuconnect/static/pretix_secuconnect/.gitkeep
pretix_secuconnect/static/pretix_secuconnect/logo.png
pretix_secuconnect/templates/pretix_secuconnect/.gitkeep
pretix_secuconnect/templates/pretix_secuconnect/checkout_payment_confirm.html
pretix_secuconnect/templates/pretix_secuconnect/checkout_payment_form.html
pretix_secuconnect/templates/pretix_secuconnect/control.html
pretix_secuconnect/templates/pretix_secuconnect/pending.html
pretix_secuconnect/templates/pretix_secuconnect/redirect.html
pretix_secuconnect-1.0.3.dist-info/licenses/LICENSE
pretix_secuconnect-1.0.3.dist-info/METADATA
pretix_secuconnect-1.0.3.dist-info/WHEEL
pretix_secuconnect-1.0.3.dist-info/entry_points.txt
pretix_secuconnect-1.0.3.dist-info/top_level.txt
pretix_secuconnect-1.0.3.dist-info/RECORD
