Metadata-Version: 2.4
Name: pretix-secuconnect
Version: 1.0.3
Summary: Accept payments through secuconnect.
Author-email: pretix team <support@pretix.eu>
Maintainer-email: pretix team <support@pretix.eu>
License: Apache
Project-URL: homepage, https://github.com/pretix/pretix-secuconnect
Project-URL: repository, https://github.com/pretix/pretix-secuconnect
Keywords: pretix
License-File: LICENSE
Dynamic: license-file
